get_children_parents_recursively/LICENSE
get_children_parents_recursively/README.MD
get_children_parents_recursively/__init__.py
get_children_parents_recursively/requirements.txt
get_children_parents_recursively/thirdparty.json
get_children_parents_recursively-0.10.dist-info/LICENSE.rst
get_children_parents_recursively-0.10.dist-info/METADATA
get_children_parents_recursively-0.10.dist-info/WHEEL
get_children_parents_recursively-0.10.dist-info/top_level.txt
get_children_parents_recursively-0.10.dist-info/RECORD
